README.md
setup.py
saltshaker/__init__.py
saltshaker/config/__init__.py
saltshaker/config/configparsing.py
saltshaker/config/loggerconfig.py
saltshaker/config/training.conf
saltshaker/data/__init__.py
saltshaker/data/kcor/__init__.py
saltshaker/data/kcor/kcor_CFA41.fits
saltshaker/data/kcor/kcor_CFA42.fits
saltshaker/data/kcor/kcor_CSPDR3.fits
saltshaker/data/kcor/kcor_DECam.fits
saltshaker/data/kcor/kcor_Hicken09.fits
saltshaker/data/kcor/kcor_Other_LOWZ.fits
saltshaker/data/kcor/kcor_PS1_none.fits
saltshaker/data/kcor/kcor_PS1_offsets.fits
saltshaker/data/kcor/kcor_SDSS_Swope_Keplercam.fits
saltshaker/data/kcor/kcor_SDSS_Swope_Keplercam_stupidsnana.fits
saltshaker/data/kcor/kcor_SNLS.fits
saltshaker/data/kcor/kcor_lowz_BayeSN.fits
saltshaker/data/kcor/modSpecTable.py
saltshaker/initfiles/Bessell90_B.dat
saltshaker/initfiles/Bessell90_V.dat
saltshaker/initfiles/Kaepora_dm15_0.94.txt
saltshaker/initfiles/Kaepora_dm15_1.1.txt
saltshaker/initfiles/__init__.py
saltshaker/initfiles/flatnu.dat
saltshaker/initfiles/hsiao07.dat
saltshaker/initfiles/salt2_color_correction.dat
saltshaker/initfiles/salt2_color_dispersion.dat
saltshaker/initfiles/salt2_ext_template_0.dat
saltshaker/initfiles/salt2_ext_template_1.dat
saltshaker/initfiles/salt2_lc_dispersion_scaling.dat
saltshaker/initfiles/salt2_lc_relative_covariance_01.dat
saltshaker/initfiles/salt2_lc_relative_variance_0.dat
saltshaker/initfiles/salt2_lc_relative_variance_1.dat
saltshaker/initfiles/salt2_spec_covariance_01.dat
saltshaker/initfiles/salt2_spec_variance_0.dat
saltshaker/initfiles/salt2_spec_variance_1.dat
saltshaker/initfiles/salt2_template_0.dat
saltshaker/initfiles/salt2_template_1.dat
saltshaker/initfiles/vegased_2004_stis.txt
saltshaker/pipeline/__init__.py
saltshaker/pipeline/pipeline.py
saltshaker/pipeline/runpipe.py
saltshaker/pipeline/validplot.py
saltshaker/plotting/__init__.py
saltshaker/plotting/cosmo.py
saltshaker/plotting/getmu.py
saltshaker/plotting/ovdatamc.py
saltshaker/plotting/plots.py
saltshaker_sn.egg-info/PKG-INFO
saltshaker_sn.egg-info/SOURCES.txt
saltshaker_sn.egg-info/dependency_links.txt
saltshaker_sn.egg-info/requires.txt
saltshaker_sn.egg-info/top_level.txt